yta_editor_common/__init__.py
yta_editor_common/frame/__init__.py
yta_editor_common/frame/core/__init__.py
yta_editor_common/frame/core/domain.py
yta_editor_common/frame/cpu/__init__.py
yta_editor_common/frame/cpu/adapters.py
yta_editor_common/frame/gpu/__init__.py
yta_editor_common/frame/gpu/adapters.py
yta_editor_common/frame/helper.py
yta_editor_common/frame/registry.py
yta_editor_common/frame.py
yta_editor_common-0.0.3.dist-info/licenses/LICENSE
yta_editor_common-0.0.3.dist-info/METADATA
yta_editor_common-0.0.3.dist-info/WHEEL
yta_editor_common-0.0.3.dist-info/RECORD
