Metadata-Version: 2.4
Name: yta-editor-common
Version: 0.0.3
Summary: Youtube Autonomous Main Editor Common module
License-File: LICENSE
Author: danialcala94
Author-email: danielalcalavalera@gmail.com
Requires-Python: ==3.9
Classifier: Programming Language :: Python :: 3
Classifier: Programming Language :: Python :: 3.9
Requires-Dist: yta_programming (>=0.0.1,<1.0.0)
